setup.cfg
setup.py
./__init__.py
./carrier.py
./carrier.xml
./sale.py
./stock.py
./tryton.cfg
./tests/scenario_carrier_zone.rst
./view/carrier_form.xml
./view/carrierzone_price_list_form.xml
./view/carrierzone_price_list_tree.xml
openlabs_carrier_zone.egg-info/PKG-INFO
openlabs_carrier_zone.egg-info/SOURCES.txt
openlabs_carrier_zone.egg-info/dependency_links.txt
openlabs_carrier_zone.egg-info/entry_points.txt
openlabs_carrier_zone.egg-info/not-zip-safe
openlabs_carrier_zone.egg-info/requires.txt
openlabs_carrier_zone.egg-info/top_level.txt
tests/__init__.py
tests/test_carrier.py
tests/test_views_depends.py